gateguard-1.3.2.dist-info/top_level.txt
gateguard-1.3.2.dist-info/WHEEL
gateguard-1.3.2.dist-info/METADATA
gateguard-1.3.2.dist-info/RECORD
gateguard-1.3.2.dist-info/metadata.json
gateguard-1.3.2.dist-info/DESCRIPTION.rst
gateguard/schema.py
gateguard/__init__.py
gateguard/exceptions.py
gateguard/fields.py
