Metadata-Version: 2.0
Name: gateguard
Version: 1.3.2
Summary: Schema-based validation package
Home-page: https://github.com/pyvim/gateguard
Author: Vitalii Maslov
Author-email: me@pyvim.com
License: MIT
Download-URL: https://github.com/pyvim/gateguard/tarball/master
Keywords: validate,validation,dict,json,data,protect,schema
Platform: UNKNOWN
Classifier: Intended Audience :: Developers
Classifier: Programming Language :: Python
